odoo/addons/sale_loyalty_order_suggestion_multi_product/README.rst
odoo/addons/sale_loyalty_order_suggestion_multi_product/__init__.py
odoo/addons/sale_loyalty_order_suggestion_multi_product/__manifest__.py
odoo/addons/sale_loyalty_order_suggestion_multi_product/i18n/es.po
odoo/addons/sale_loyalty_order_suggestion_multi_product/i18n/it.po
odoo/addons/sale_loyalty_order_suggestion_multi_product/i18n/sale_loyalty_order_suggestion_multi_product.pot
odoo/addons/sale_loyalty_order_suggestion_multi_product/models/__init__.py
odoo/addons/sale_loyalty_order_suggestion_multi_product/models/sale_order.py
odoo/addons/sale_loyalty_order_suggestion_multi_product/readme/CONTRIBUTORS.md
odoo/addons/sale_loyalty_order_suggestion_multi_product/readme/DESCRIPTION.md
odoo/addons/sale_loyalty_order_suggestion_multi_product/readme/USAGE.md
odoo/addons/sale_loyalty_order_suggestion_multi_product/static/description/icon.png
odoo/addons/sale_loyalty_order_suggestion_multi_product/static/description/index.html
odoo/addons/sale_loyalty_order_suggestion_multi_product/tests/__init__.py
odoo/addons/sale_loyalty_order_suggestion_multi_product/tests/test_sale_loyalty_order_suggestion_multi_product.py
odoo/addons/sale_loyalty_order_suggestion_multi_product/wizard/__init__.py
odoo/addons/sale_loyalty_order_suggestion_multi_product/wizard/sale_loyalty_reward_wizard.py
odoo_addon_sale_loyalty_order_suggestion_multi_product-18.0.1.0.1.dist-info/METADATA
odoo_addon_sale_loyalty_order_suggestion_multi_product-18.0.1.0.1.dist-info/WHEEL
odoo_addon_sale_loyalty_order_suggestion_multi_product-18.0.1.0.1.dist-info/top_level.txt
odoo_addon_sale_loyalty_order_suggestion_multi_product-18.0.1.0.1.dist-info/RECORD
